<?xml version="1.0" encoding="UTF-8" ?>
<!-- generated by WriteConceptFile on 1374705449454 -->
<synonym>
<token canonical="dopaminergic group A13" ref_id="Hof:1082054710">
  <variant base="dopaminergic group A13" />
</token>
<token canonical="anterior amygdaloid area" ref_id="Hof:221">
  <variant base="anterior amygdaloid area" />
</token>
<token canonical="nucleus of the anterior comrnissure" ref_id="Hof:248">
  <variant base="nucleus of the anterior comrnissure" />
</token>
<token canonical="nucleus accumbens" ref_id="Hof:259">
  <variant base="nucleus accumbens" />
</token>
<token canonical="nucleus accumbens, core" ref_id="Hof:259">
  <variant base="nucleus accumbens, core" />
</token>
<token canonical="nucleus accumbens, shell" ref_id="Hof:259">
  <variant base="nucleus accumbens, shell" />
</token>
<token canonical="anterior cingulate cortex, dorsal part" ref_id="Hof:1079109033">
  <variant base="anterior cingulate cortex, dorsal part" />
</token>
<token canonical="anterior cingulate cortex, ventral part" ref_id="Hof:-559582406">
  <variant base="anterior cingulate cortex, ventral part" />
</token>
<token canonical="anterodorsal nucleus of the thalamus" ref_id="Hof:286">
  <variant base="anterodorsal nucleus of the thalamus" />
</token>
<token canonical="anterodorsal preoptic nucleus" ref_id="Hof:-600395065">
  <variant base="anterodorsal preoptic nucleus" />
</token>
<token canonical="anterior hypothalamic area" ref_id="Hof:369">
  <variant base="anterior hypothalamic area" />
</token>
<token canonical="anterior hypothalamic nucleus" ref_id="Hof:369">
  <variant base="anterior hypothalamic nucleus" />
</token>
<token canonical="anterior hypothalamic nucleus, anterior part" ref_id="Hof:-1530712919">
  <variant base="anterior hypothalamic nucleus, anterior part" />
</token>
<token canonical="anterior hypothalamic nucleus, central part" ref_id="Hof:369">
  <variant base="anterior hypothalamic nucleus, central part" />
</token>
<token canonical="agranular insular cortex, dorsal part" ref_id="Hof:1672125268">
  <variant base="agranular insular cortex, dorsal part" />
</token>
<token canonical="agranular insular cortex, posterior part" ref_id="Hof:1672125268">
  <variant base="agranular insular cortex, posterior part" />
</token>
<token canonical="agranular insular cortex, ventral part" ref_id="Hof:1672125268">
  <variant base="agranular insular cortex, ventral part" />
</token>
<token canonical="anteromedial nucleus of the thalamus" ref_id="Hof:287">
  <variant base="anteromedial nucleus of the thalamus" />
</token>
<token canonical="nucleus ambiguus" ref_id="Hof:762">
  <variant base="nucleus ambiguus" />
</token>
<token canonical="amygdalohippocampal area" ref_id="Hof:132">
  <variant base="amygdalohippocampal area" />
</token>
<token canonical="ansiform lobe of the cerebellum, crus 1" ref_id="Hof:664">
  <variant base="ansiform lobe of the cerebellum, crus 1" />
</token>
<token canonical="ansiform lobe of the cerebellum, crus 2" ref_id="Hof:665">
  <variant base="ansiform lobe of the cerebellum, crus 2" />
</token>
<token canonical="anterior lobe of the cerebellum" ref_id="Hof:647">
  <variant base="anterior lobe of the cerebellum" />
</token>
<token canonical="accessory olfactory bulb" ref_id="Hof:709">
  <variant base="accessory olfactory bulb" />
</token>
<token canonical="anterior olfactory nucleus, dorsal part" ref_id="Hof:262">
  <variant base="anterior olfactory nucleus, dorsal part" />
</token>
<token canonical="anterior olfactory nucleus, external part" ref_id="Hof:262">
  <variant base="anterior olfactory nucleus, external part" />
</token>
<token canonical="anterior olfactory nucleus, lateral part" ref_id="Hof:262">
  <variant base="anterior olfactory nucleus, lateral part" />
</token>
<token canonical="anterior olfactory nucleus, medial part" ref_id="Hof:262">
  <variant base="anterior olfactory nucleus, medial part" />
</token>
<token canonical="anterior olfactory nucleus, ventral part" ref_id="Hof:262">
  <variant base="anterior olfactory nucleus, ventral part" />
</token>
<token canonical="area postrema" ref_id="Hof:769">
  <variant base="area postrema" />
</token>
<token canonical="amygdalopiriform transition area" ref_id="Hof:382942993">
  <variant base="amygdalopiriform transition area" />
</token>
<token canonical="anterior pretectal nucleus" ref_id="Hof:-2117802103">
  <variant base="anterior pretectal nucleus" />
</token>
<token canonical="aqueduct of Sylvius" ref_id="Hof:500">
  <variant base="aqueduct of Sylvius" />
</token>
<token canonical="arcuate nucleus of the hypothalamus" ref_id="Hof:378">
  <variant base="arcuate nucleus of the hypothalamus" />
</token>
<token canonical="amygdalostriatal transition area" ref_id="Hof:1078867249">
  <variant base="amygdalostriatal transition area" />
</token>
<token canonical="anterior tegmental nucleus" ref_id="Hof:-2523448">
  <variant base="anterior tegmental nucleus" />
</token>
<token canonical="auditory cortex, dorsal part" ref_id="Hof:587159041">
  <variant base="auditory cortex, dorsal part" />
</token>
<token canonical="primary auditory cortex" ref_id="Hof:428">
  <variant base="primary auditory cortex" />
</token>
<token canonical="auditory cortex, ventral part" ref_id="Hof:27618709">
  <variant base="auditory cortex, ventral part" />
</token>
<token canonical="anteroventral nucleus of the thalamus" ref_id="Hof:288">
  <variant base="anteroventral nucleus of the thalamus" />
</token>
<token canonical="accessory facial nucleus" ref_id="Hof:622">
  <variant base="accessory facial nucleus" />
</token>
<token canonical="anteroventral preoptic nucleus" ref_id="Hof:169910044">
  <variant base="anteroventral preoptic nucleus" />
</token>
<token canonical="anteroventral periventricular nucleus of the hypothalamus" ref_id="Hof:365">
  <variant base="anteroventral periventricular nucleus of the hypothalamus" />
</token>
<token canonical="anterior commissure, olfactory limb" ref_id="Hof:188">
  <variant base="anterior commissure, olfactory limb" />
</token>
<token canonical="anterior commissure, temporal limb" ref_id="Hof:189">
  <variant base="anterior commissure, temporal limb" />
</token>
<token canonical="arcuate fibers (medial lemniscus)" ref_id="Hof:792">
  <variant base="arcuate fibers (medial lemniscus)" />
</token>
<token canonical="alveus" ref_id="Hof:168">
  <variant base="alveus" />
</token>
<token canonical="amygdalar capsule" ref_id="Hof:-1001478284">
  <variant base="amygdalar capsule" />
</token>
<token canonical="ansoparamedian fissure" ref_id="Hof:-2128873639">
  <variant base="ansoparamedian fissure" />
</token>
<token canonical="Barrington nucleus" ref_id="Hof:1842717954">
  <variant base="Barrington nucleus" />
</token>
<token canonical="serotonergic B9 field" ref_id="Hof:-718477323">
  <variant base="serotonergic B9 field" />
</token>
<token canonical="bed nucleus of the accessory olfactory tract" ref_id="Hof:740708606">
  <variant base="bed nucleus of the accessory olfactory tract" />
</token>
<token canonical="barrel field" ref_id="Hof:419">
  <variant base="barrel field" />
</token>
<token canonical="basolateral nucleus of the amygdala" ref_id="Hof:228">
  <variant base="basolateral nucleus of the amygdala" />
</token>
<token canonical="basolateral amygdaloid nucleus, posterior part" ref_id="Hof:228">
  <variant base="basolateral amygdaloid nucleus, posterior part" />
</token>
<token canonical="basolateral nucleus of the amygdala, ventral part" ref_id="Hof:228">
  <variant base="basolateral nucleus of the amygdala, ventral part" />
</token>
<token canonical="basomedial nucleus of the amygdala, anterior part" ref_id="Hof:231">
  <variant base="basomedial nucleus of the amygdala, anterior part" />
</token>
<token canonical="basomedial nucleus of the amygdala, posterior part" ref_id="Hof:231">
  <variant base="basomedial nucleus of the amygdala, posterior part" />
</token>
<token canonical="bed nucleus of the stria medullaris" ref_id="Hof:1239388469">
  <variant base="bed nucleus of the stria medullaris" />
</token>
<token canonical="bed nucleus of the stria terminalis, anterodorsal part ," ref_id="Hof:249">
  <variant base="bed nucleus of the stria terminalis, anterodorsal part ," />
</token>
<token canonical="bed nucleus of the stria terminalis, anteroventral part" ref_id="Hof:249">
  <variant base="bed nucleus of the stria terminalis, anteroventral part" />
</token>
<token canonical="bed nucleus of the stria terminalis, interfascicular part" ref_id="Hof:249">
  <variant base="bed nucleus of the stria terminalis, interfascicular part" />
</token>
<token canonical="bed nucleus of the stria terminalis, oval part" ref_id="Hof:249">
  <variant base="bed nucleus of the stria terminalis, oval part" />
</token>
<token canonical="bed nucleus of the stria terminalis, posterointermediate part" ref_id="Hof:249">
  <variant base="bed nucleus of the stria terminalis, posterointermediate part" />
</token>
<token canonical="bed nucleus of the stria terminalis, posterolateral part" ref_id="Hof:249">
  <variant base="bed nucleus of the stria terminalis, posterolateral part" />
</token>
<token canonical="bed nucleus of the stria terminalis, posteromedial part" ref_id="Hof:249">
  <variant base="bed nucleus of the stria terminalis, posteromedial part" />
</token>
<token canonical="bed nucleus of the stria terminalis, subcommissural part" ref_id="Hof:249">
  <variant base="bed nucleus of the stria terminalis, subcommissural part" />
</token>
<token canonical="brachium of the inferior colliculus" ref_id="Hof:471">
  <variant base="brachium of the inferior colliculus" />
</token>
<token canonical="brachium of the superior colliculus" ref_id="Hof:465">
  <variant base="brachium of the superior colliculus" />
</token>
<token canonical="CA1 field of Ammon&apos;s horn" ref_id="Hof:165">
  <variant base="CA1 field of Ammon&apos;s horn" />
</token>
<token canonical="CA2 field of Ammon&apos;s horn" ref_id="Hof:166">
  <variant base="CA2 field of Ammon&apos;s horn" />
</token>
<token canonical="CA3 field of Ammon&apos;s horn" ref_id="Hof:167">
  <variant base="CA3 field of Ammon&apos;s horn" />
</token>
<token canonical="calbindin-containing nucleus of the pons" ref_id="Hof:-1846360614">
  <variant base="calbindin-containing nucleus of the pons" />
</token>
<token canonical="cortico-amygdaloid transition zone" ref_id="Hof:-202312166">
  <variant base="cortico-amygdaloid transition zone" />
</token>
<token canonical="central canal" ref_id="Hof:770">
  <variant base="central canal" />
</token>
<token canonical="central nucleus of the amygdala, central part" ref_id="Hof:225">
  <variant base="central nucleus of the amygdala, central part" />
</token>
<token canonical="central nucleus of the amygdala, lateral part" ref_id="Hof:225">
  <variant base="central nucleus of the amygdala, lateral part" />
</token>
<token canonical="central nucleus of the amygdala, medial part" ref_id="Hof:225">
  <variant base="central nucleus of the amygdala, medial part" />
</token>
<token canonical="central lobe of the cerebellum, lobule 2" ref_id="Hof:1762951785">
  <variant base="central lobe of the cerebellum, lobule 2" />
</token>
<token canonical="central lobe of the cerebellum, lobule 3" ref_id="Hof:991540460">
  <variant base="central lobe of the cerebellum, lobule 3" />
</token>
<token canonical="central lobe of the cerebellum, lobule 4" ref_id="Hof:656">
  <variant base="central lobe of the cerebellum, lobule 4" />
</token>
<token canonical="central lobe of the cerebellum, lobules 4-5" ref_id="Hof:656">
  <variant base="central lobe of the cerebellum, lobules 4-5" />
</token>
<token canonical="central lobe of the cerebellum, lobule 6" ref_id="Hof:671">
  <variant base="central lobe of the cerebellum, lobule 6" />
</token>
<token canonical="central lobe of the cerebellum, lobule 7" ref_id="Hof:1774385344">
  <variant base="central lobe of the cerebellum, lobule 7" />
</token>
<token canonical="central lobe of the cerebellum, lobule 8" ref_id="Hof:674">
  <variant base="central lobe of the cerebellum, lobule 8" />
</token>
<token canonical="ccntral lobe of the cerebellum, lobule 9" ref_id="Hof:675">
  <variant base="ccntral lobe of the cerebellum, lobule 9" />
</token>
<token canonical="central lobe of the cerebellum, lobule 10" ref_id="Hof:678">
  <variant base="central lobe of the cerebellum, lobule 10" />
</token>
<token canonical="central gray matter" ref_id="Hof:753">
  <variant base="central gray matter" />
</token>
<token canonical="central lateral nucleus of the thalamus" ref_id="Hof:303">
  <variant base="central lateral nucleus of the thalamus" />
</token>
<token canonical="claustrum" ref_id="Hof:234">
  <variant base="claustrum" />
</token>
<token canonical="central linear nucleus of the raphe" ref_id="Hof:510">
  <variant base="central linear nucleus of the raphe" />
</token>
<token canonical="central medial nucleus of the thalamus" ref_id="Hof:304">
  <variant base="central medial nucleus of the thalamus" />
</token>
<token canonical="granular layer of the cochlear nuclei" ref_id="Hof:717">
  <variant base="granular layer of the cochlear nuclei" />
</token>
<token canonical="cortical nucleus of the amygdala, anterior part" ref_id="Hof:727">
  <variant base="cortical nucleus of the amygdala, anterior part" />
</token>
<token canonical="cortical nucleus of the amygdala, posterolateral part" ref_id="Hof:148">
  <variant base="cortical nucleus of the amygdala, posterolateral part" />
</token>
<token canonical="cortical nucleus of the amygdala, posteromedial part" ref_id="Hof:148">
  <variant base="cortical nucleus of the amygdala, posteromedial part" />
</token>
<token canonical="copula pyramidis" ref_id="Hof:2081898093">
  <variant base="copula pyramidis" />
</token>
<token canonical="caudate-putamen" ref_id="Hof:207">
  <variant base="caudate-putamen" />
</token>
<token canonical="central superior nucleus of the raphe, lateral part" ref_id="Hof:-2140923109">
  <variant base="central superior nucleus of the raphe, lateral part" />
</token>
<token canonical="central superior nucleus of the raphe, medial part" ref_id="Hof:-1560544054">
  <variant base="central superior nucleus of the raphe, medial part" />
</token>
<token canonical="cuneate nucleus" ref_id="Hof:764">
  <variant base="cuneate nucleus" />
</token>
<token canonical="cuneiform nucleus" ref_id="Hof:493">
  <variant base="cuneiform nucleus" />
</token>
<token canonical="cerebellar commissure" ref_id="Hof:-1590685356">
  <variant base="cerebellar commissure" />
</token>
<token canonical="corpus callosum" ref_id="Hof:173">
  <variant base="corpus callosum" />
</token>
<token canonical="corpus callosum, genu" ref_id="Hof:176">
  <variant base="corpus callosum, genu" />
</token>
<token canonical="cingulum bundle" ref_id="Hof:541">
  <variant base="cingulum bundle" />
</token>
<token canonical="comrnissure of the inferior colliculus" ref_id="Hof:472">
  <variant base="comrnissure of the inferior colliculus" />
</token>
<token canonical="cerebral peduncle" ref_id="Hof:478">
  <variant base="cerebral peduncle" />
</token>
<token canonical="commissure of the superior colliculus" ref_id="Hof:466">
  <variant base="commissure of the superior colliculus" />
</token>
<token canonical="corticospinal tract" ref_id="Hof:373">
  <variant base="corticospinal tract" />
</token>
<token canonical="cuneate fasciculus" ref_id="Hof:116">
  <variant base="cuneate fasciculus" />
</token>
<token canonical="dorsal cochlear nucleus" ref_id="Hof:718">
  <variant base="dorsal cochlear nucleus" />
</token>
<token canonical="dentate gyrus" ref_id="Hof:161">
  <variant base="dentate gyrus" />
</token>
<token canonical="dorsal horn of the spinal cord" ref_id="Hof:976">
  <variant base="dorsal horn of the spinal cord" />
</token>
<token canonical="dorsal nucleus of the lateral lemniscus" ref_id="Hof:586">
  <variant base="dorsal nucleus of the lateral lemniscus" />
</token>
<token canonical="dorsomedial hypothalamic nucleus" ref_id="Hof:380">
  <variant base="dorsomedial hypothalamic nucleus" />
</token>
<token canonical="dorsomedial hypothalamic nucleus, dorsal part" ref_id="Hof:-614408469">
  <variant base="dorsomedial hypothalamic nucleus, dorsal part" />
</token>
<token canonical="dorsomedial hypothalamic nucleus, ventral part" ref_id="Hof:-1050184726">
  <variant base="dorsomedial hypothalamic nucleus, ventral part" />
</token>
<token canonical="dorsal motor nucleus of the vagus" ref_id="Hof:752">
  <variant base="dorsal motor nucleus of the vagus" />
</token>
<token canonical="dentate nucleus" ref_id="Hof:680">
  <variant base="dentate nucleus" />
</token>
<token canonical="dentate nucleus, parvicellular part" ref_id="Hof:680">
  <variant base="dentate nucleus, parvicellular part" />
</token>
<token canonical="dorsal peduncular area" ref_id="Hof:-1916286841">
  <variant base="dorsal peduncular area" />
</token>
<token canonical="dorsal nucleus of the raphe" ref_id="Hof:503">
  <variant base="dorsal nucleus of the raphe" />
</token>
<token canonical="dorsal terminal nucleus of the accessory optic tract" ref_id="Hof:469026879">
  <variant base="dorsal terminal nucleus of the accessory optic tract" />
</token>
<token canonical="dorsal tegmental nucleus" ref_id="Hof:508">
  <variant base="dorsal tegmental nucleus" />
</token>
<token canonical="dorsal fornix" ref_id="Hof:3">
  <variant base="dorsal fornix" />
</token>
<token canonical="deep gray layer of the superior colliculus" ref_id="Hof:515">
  <variant base="deep gray layer of the superior colliculus" />
</token>
<token canonical="dorsal hippocampal commissure" ref_id="Hof:255">
  <variant base="dorsal hippocampal commissure" />
</token>
<token canonical="dorsal spinocerebellar tract" ref_id="Hof:804">
  <variant base="dorsal spinocerebellar tract" />
</token>
<token canonical="decussation of the superior cerebellar peduncle" ref_id="Hof:518">
  <variant base="decussation of the superior cerebellar peduncle" />
</token>
<token canonical="dorsal tegmental decussation" ref_id="Hof:514">
  <variant base="dorsal tegmental decussation" />
</token>
<token canonical="deep white layer of the superior colliculus" ref_id="Hof:515">
  <variant base="deep white layer of the superior colliculus" />
</token>
<token canonical="ectorhinal cortex" ref_id="Hof:-454495102">
  <variant base="ectorhinal cortex" />
</token>
<token canonical="external cuneate nucleus" ref_id="Hof:765">
  <variant base="external cuneate nucleus" />
</token>
<token canonical="entorhinal cortex, lateral part" ref_id="Hof:1750006372">
  <variant base="entorhinal cortex, lateral part" />
</token>
<token canonical="entorhinal cortex, medial part" ref_id="Hof:1232032700">
  <variant base="entorhinal cortex, medial part" />
</token>
<token canonical="endopiriform nucleus, dorsal part" ref_id="Hof:40282260">
  <variant base="endopiriform nucleus, dorsal part" />
</token>
<token canonical="endopiriform nucleus, ventral part" ref_id="Hof:1846799091">
  <variant base="endopiriform nucleus, ventral part" />
</token>
<token canonical="ethmoidal nucleus of the thalamus" ref_id="Hof:-399819267">
  <variant base="ethmoidal nucleus of the thalamus" />
</token>
<token canonical="Edinger-Westphal nucleus" ref_id="Hof:489">
  <variant base="Edinger-Westphal nucleus" />
</token>
<token canonical="external capsule" ref_id="Hof:235">
  <variant base="external capsule" />
</token>
<token canonical="external medullary lamina of the thalamus" ref_id="Hof:350">
  <variant base="external medullary lamina of the thalamus" />
</token>
<token canonical="fasciola cinerea" ref_id="Hof:158">
  <variant base="fasciola cinerea" />
</token>
<token canonical="fields of Forel" ref_id="Hof:407">
  <variant base="fields of Forel" />
</token>
<token canonical="flocculus" ref_id="Hof:677">
  <variant base="flocculus" />
</token>
<token canonical="fastigial nucleus" ref_id="Hof:687">
  <variant base="fastigial nucleus" />
</token>
<token canonical="frontal association area" ref_id="Hof:101">
  <variant base="frontal association area" />
</token>
<token canonical="frontal pole" ref_id="Hof:38">
  <variant base="frontal pole" />
</token>
<token canonical="corpus callosum, anterior forceps" ref_id="Hof:174">
  <variant base="corpus callosum, anterior forceps" />
</token>
<token canonical="fimbria" ref_id="Hof:169">
  <variant base="fimbria" />
</token>
<token canonical="posterior forceps" ref_id="Hof:179">
  <variant base="posterior forceps" />
</token>
<token canonical="fasciculus retroflexus" ref_id="Hof:1008354279">
  <variant base="fasciculus retroflexus" />
</token>
<token canonical="fornix" ref_id="Hof:250">
  <variant base="fornix" />
</token>
<token canonical="globus pallidus, lateral part" ref_id="Hof:214">
  <variant base="globus pallidus, lateral part" />
</token>
<token canonical="globus pallidus, medial part" ref_id="Hof:215">
  <variant base="globus pallidus, medial part" />
</token>
<token canonical="gracile nucleus" ref_id="Hof:763">
  <variant base="gracile nucleus" />
</token>
<token canonical="gigantocellular reticular nucleus" ref_id="Hof:727">
  <variant base="gigantocellular reticular nucleus" />
</token>
<token canonical="gustatory cortex" ref_id="Hof:434">
  <variant base="gustatory cortex" />
</token>
<token canonical="glomerular layer" ref_id="Hof:261">
  <variant base="glomerular layer" />
</token>
<token canonical="granule cell layer" ref_id="Hof:261">
  <variant base="granule cell layer" />
</token>
<token canonical="gracile fasciculus" ref_id="Hof:117">
  <variant base="gracile fasciculus" />
</token>
<token canonical="genu of the facial nerve" ref_id="Hof:576">
  <variant base="genu of the facial nerve" />
</token>
<token canonical="habenular commissure" ref_id="Hof:282">
  <variant base="habenular commissure" />
</token>
<token canonical="hippocampal fissure" ref_id="Hof:23">
  <variant base="hippocampal fissure" />
</token>
<token canonical="intercalated nucleus of the amygdala" ref_id="Hof:232">
  <variant base="intercalated nucleus of the amygdala" />
</token>
<token canonical="interanterodorsal nucleus of the thalamus" ref_id="Hof:311">
  <variant base="interanterodorsal nucleus of the thalamus" />
</token>
<token canonical="interanteromedial nucleus of the thalamus" ref_id="Hof:311">
  <variant base="interanteromedial nucleus of the thalamus" />
</token>
<token canonical="inferior colliculus, central nucleus" ref_id="Hof:470">
  <variant base="inferior colliculus, central nucleus" />
</token>
<token canonical="inferior colliculus, dorsal nucleus" ref_id="Hof:468">
  <variant base="inferior colliculus, dorsal nucleus" />
</token>
<token canonical="inferior colliculus, external nucleus" ref_id="Hof:469">
  <variant base="inferior colliculus, external nucleus" />
</token>
<token canonical="intercollicular nucleus" ref_id="Hof:1536115395">
  <variant base="intercollicular nucleus" />
</token>
<token canonical="interfascicular nucleus" ref_id="Hof:-1903570078">
  <variant base="interfascicular nucleus" />
</token>
<token canonical="indusium griseum" ref_id="Hof:155">
  <variant base="indusium griseum" />
</token>
<token canonical="intergeniculate leaflet" ref_id="Hof:-1849049562">
  <variant base="intergeniculate leaflet" />
</token>
<token canonical="oculomotor nucleus" ref_id="Hof:483">
  <variant base="oculomotor nucleus" />
</token>
<token canonical="infralimbic area" ref_id="Hof:625473982">
  <variant base="infralimbic area" />
</token>
<token canonical="intermediate nucleus of the lateral lemniscus" ref_id="Hof:943298164">
  <variant base="intermediate nucleus of the lateral lemniscus" />
</token>
<token canonical="intermediodorsal nucleus of the thalamus" ref_id="Hof:1520382872">
  <variant base="intermediodorsal nucleus of the thalamus" />
</token>
<token canonical="interstitial nucleus of Cajal" ref_id="Hof:506">
  <variant base="interstitial nucleus of Cajal" />
</token>
<token canonical="inferior olivary complex, central nucleus" ref_id="Hof:-1061420189">
  <variant base="inferior olivary complex, central nucleus" />
</token>
<token canonical="inferior olivary complex, cap of Kooy" ref_id="Hof:-1614262838">
  <variant base="inferior olivary complex, cap of Kooy" />
</token>
<token canonical="inferior olivary complex, dorsal accessory nucleus" ref_id="Hof:747">
  <variant base="inferior olivary complex, dorsal accessory nucleus" />
</token>
<token canonical="inferior olivary complex, dorsomedial nucleus" ref_id="Hof:-1793538894">
  <variant base="inferior olivary complex, dorsomedial nucleus" />
</token>
<token canonical="inferior olivary complex, medial accessory nucleus" ref_id="Hof:748">
  <variant base="inferior olivary complex, medial accessory nucleus" />
</token>
<token canonical="inferior olivary complex, principal olive" ref_id="Hof:746">
  <variant base="inferior olivary complex, principal olive" />
</token>
<token canonical="nucleus interpositus" ref_id="Hof:264">
  <variant base="nucleus interpositus" />
</token>
<token canonical="interpeduncular nucleus" ref_id="Hof:513">
  <variant base="interpeduncular nucleus" />
</token>
<token canonical="interpeduncular nucleus, central part" ref_id="Hof:513">
  <variant base="interpeduncular nucleus, central part" />
</token>
<token canonical="interpeduncular nucleus, dorsolateral part" ref_id="Hof:513">
  <variant base="interpeduncular nucleus, dorsolateral part" />
</token>
<token canonical="interpeduncular nucleus, dorsomedial part" ref_id="Hof:513">
  <variant base="interpeduncular nucleus, dorsomedial part" />
</token>
<token canonical="interpeduncular nucleus, intermediate part" ref_id="Hof:513">
  <variant base="interpeduncular nucleus, intermediate part" />
</token>
<token canonical="interpeduncular nucleus, lateral part" ref_id="Hof:513">
  <variant base="interpeduncular nucleus, lateral part" />
</token>
<token canonical="interpeduncular nucleus, rostra1 part" ref_id="Hof:513">
  <variant base="interpeduncular nucleus, rostra1 part" />
</token>
<token canonical="intermediate reticular nucleus" ref_id="Hof:-276469037">
  <variant base="intermediate reticular nucleus" />
</token>
<token canonical="insula of Calleja" ref_id="Hof:258">
  <variant base="insula of Calleja" />
</token>
<token canonical="insula of Calleja major" ref_id="Hof:792">
  <variant base="insula of Calleja major" />
</token>
<token canonical="inferior salivatory nucleus" ref_id="Hof:761">
  <variant base="inferior salivatory nucleus" />
</token>
<token canonical="intertrigeminal nucleus" ref_id="Hof:179065176">
  <variant base="intertrigeminal nucleus" />
</token>
<token canonical="trochlear nucleus" ref_id="Hof:504">
  <variant base="trochlear nucleus" />
</token>
<token canonical="intermediate acoustic stria" ref_id="Hof:599">
  <variant base="intermediate acoustic stria" />
</token>
<token canonical="intercrural fissure" ref_id="Hof:658">
  <variant base="intercrural fissure" />
</token>
<token canonical="inferior cerebellar peduncle" ref_id="Hof:778">
  <variant base="inferior cerebellar peduncle" />
</token>
<token canonical="intermediate gray layer of the superior colliculus" ref_id="Hof:515">
  <variant base="intermediate gray layer of the superior colliculus" />
</token>
<token canonical="internal capsule" ref_id="Hof:180">
  <variant base="internal capsule" />
</token>
<token canonical="interpeduncular fossa" ref_id="Hof:480">
  <variant base="interpeduncular fossa" />
</token>
<token canonical="internal plexiform layer" ref_id="Hof:261">
  <variant base="internal plexiform layer" />
</token>
<token canonical="interventricular foramen" ref_id="Hof:430">
  <variant base="interventricular foramen" />
</token>
<token canonical="intermediate white layer of the superior colliculus" ref_id="Hof:515">
  <variant base="intermediate white layer of the superior colliculus" />
</token>
<token canonical="K&#65533;lliker-Fuse nucleus" ref_id="Hof:757">
  <variant base="K&#65533;lliker-Fuse nucleus" />
</token>
<token canonical="lateral nucleus of the amygdala" ref_id="Hof:227">
  <variant base="lateral nucleus of the amygdala" />
</token>
<token canonical="lateral nucleus of the amygdala, dorsal part" ref_id="Hof:227">
  <variant base="lateral nucleus of the amygdala, dorsal part" />
</token>
<token canonical="lateral nucleus of the amygdala, ventral part" ref_id="Hof:227">
  <variant base="lateral nucleus of the amygdala, ventral part" />
</token>
<token canonical="locus ceruleus" ref_id="Hof:578">
  <variant base="locus ceruleus" />
</token>
<token canonical="lateral cervical nucleus" ref_id="Hof:961">
  <variant base="lateral cervical nucleus" />
</token>
<token canonical="laterodorsal nucleus of the thalamus" ref_id="Hof:309">
  <variant base="laterodorsal nucleus of the thalamus" />
</token>
<token canonical="laterodorsal nucleus of the thalamus, dorsomedial part" ref_id="Hof:309">
  <variant base="laterodorsal nucleus of the thalamus, dorsomedial part" />
</token>
<token canonical="laterodorsal tegmental nucleus" ref_id="Hof:282">
  <variant base="laterodorsal tegmental nucleus" />
</token>
<token canonical="laterodorsal nucleus of the thalamus, ventrolateral part" ref_id="Hof:309">
  <variant base="laterodorsal nucleus of the thalamus, ventrolateral part" />
</token>
<token canonical="lambdoid zone of the septum" ref_id="Hof:1661192099">
  <variant base="lambdoid zone of the septum" />
</token>
<token canonical="lateral geniculate nucleus, dorsal part" ref_id="Hof:336">
  <variant base="lateral geniculate nucleus, dorsal part" />
</token>
<token canonical="lateral geniculate nucleus, ventral part" ref_id="Hof:337">
  <variant base="lateral geniculate nucleus, ventral part" />
</token>
<token canonical="lateral geniculate nucleus, ventrolateral part" ref_id="Hof:337">
  <variant base="lateral geniculate nucleus, ventrolateral part" />
</token>
<token canonical="lateral geniculate nucleus, ventromedial part" ref_id="Hof:337">
  <variant base="lateral geniculate nucleus, ventromedial part" />
</token>
<token canonical="lateral habenula" ref_id="Hof:278">
  <variant base="lateral habenula" />
</token>
<token canonical="lateral hypothalamic area" ref_id="Hof:409">
  <variant base="lateral hypothalamic area" />
</token>
<token canonical="linear nucleus of the medulla" ref_id="Hof:-2010735025">
  <variant base="linear nucleus of the medulla" />
</token>
<token canonical="lingula" ref_id="Hof:654">
  <variant base="lingula" />
</token>
<token canonical="lateral mammillary nucleus" ref_id="Hof:396">
  <variant base="lateral mammillary nucleus" />
</token>
<token canonical="lateral posterior nucleus of the thalamus" ref_id="Hof:310">
  <variant base="lateral posterior nucleus of the thalamus" />
</token>
<token canonical="lateral preoptic area" ref_id="Hof:364">
  <variant base="lateral preoptic area" />
</token>
<token canonical="lateral reticular nucleus" ref_id="Hof:724">
  <variant base="lateral reticular nucleus" />
</token>
<token canonical="lateral reticular nucleus, parvicellular part" ref_id="Hof:724">
  <variant base="lateral reticular nucleus, parvicellular part" />
</token>
<token canonical="lateral septum nucleus, dorsal part" ref_id="Hof:243">
  <variant base="lateral septum nucleus, dorsal part" />
</token>
<token canonical="lateral septum nucleus, intermediate part" ref_id="Hof:243">
  <variant base="lateral septum nucleus, intermediate part" />
</token>
<token canonical="lateral striatal stripe" ref_id="Hof:-1030005175">
  <variant base="lateral striatal stripe" />
</token>
<token canonical="lateral septum nucleus, ventral part" ref_id="Hof:243">
  <variant base="lateral septum nucleus, ventral part" />
</token>
<token canonical="lateral vestibular nucleus" ref_id="Hof:713">
  <variant base="lateral vestibular nucleus" />
</token>
<token canonical="lateral lemniscus" ref_id="Hof:605">
  <variant base="lateral lemniscus" />
</token>
<token canonical="lateral olfactory tract" ref_id="Hof:265">
  <variant base="lateral olfactory tract" />
</token>
<token canonical="lateral olfactory tract, dorsal limb" ref_id="Hof:1950519601">
  <variant base="lateral olfactory tract, dorsal limb" />
</token>
<token canonical="magnocellular preoptic nucleus" ref_id="Hof:21827536">
  <variant base="magnocellular preoptic nucleus" />
</token>
<token canonical="medial accessory oculomotor nucleus" ref_id="Hof:621278852">
  <variant base="medial accessory oculomotor nucleus" />
</token>
<token canonical="magnocellular reticular nucleus" ref_id="Hof:-270591433">
  <variant base="magnocellular reticular nucleus" />
</token>
<token canonical="mediodorsal nucleus of the thalamus" ref_id="Hof:295">
  <variant base="mediodorsal nucleus of the thalamus" />
</token>
<token canonical="medullary reticular nucleus, dorsal part" ref_id="Hof:1745472156">
  <variant base="medullary reticular nucleus, dorsal part" />
</token>
<token canonical="medullary reticular nucleus, ventral part" ref_id="Hof:-486572827">
  <variant base="medullary reticular nucleus, ventral part" />
</token>
<token canonical="median eminence" ref_id="Hof:385">
  <variant base="median eminence" />
</token>
<token canonical="medial nucleus of the amygdala, dorsal part" ref_id="Hof:728">
  <variant base="medial nucleus of the amygdala, dorsal part" />
</token>
<token canonical="medial nucleus of the amygdala, posterodorsal part" ref_id="Hof:728">
  <variant base="medial nucleus of the amygdala, posterodorsal part" />
</token>
<token canonical="medial nucleus of the amygdala, posteroventral part" ref_id="Hof:728">
  <variant base="medial nucleus of the amygdala, posteroventral part" />
</token>
<token canonical="medial nucleus of the amygdala, ventral part" ref_id="Hof:728">
  <variant base="medial nucleus of the amygdala, ventral part" />
</token>
<token canonical="median preoptic nucleus" ref_id="Hof:361">
  <variant base="median preoptic nucleus" />
</token>
<token canonical="mesencephalic nucleus of the trigeminal nerve" ref_id="Hof:550">
  <variant base="mesencephalic nucleus of the trigeminal nerve" />
</token>
<token canonical="medial geniculate nucleus, dorsal part" ref_id="Hof:339">
  <variant base="medial geniculate nucleus, dorsal part" />
</token>
<token canonical="medial geniculate nucleus, medial part" ref_id="Hof:341">
  <variant base="medial geniculate nucleus, medial part" />
</token>
<token canonical="medial geniculate nucleus, ventral part" ref_id="Hof:340">
  <variant base="medial geniculate nucleus, ventral part" />
</token>
<token canonical="medial habenula" ref_id="Hof:279">
  <variant base="medial habenula" />
</token>
<token canonical="medial mammillary nucleus, lateral part" ref_id="Hof:399">
  <variant base="medial mammillary nucleus, lateral part" />
</token>
<token canonical="medial mammillary nucleus" ref_id="Hof:397">
  <variant base="medial mammillary nucleus" />
</token>
<token canonical="medial mammillary nucleus, median part" ref_id="Hof:-2033509">
  <variant base="medial mammillary nucleus, median part" />
</token>
<token canonical="main olfactory bulb" ref_id="Hof:261">
  <variant base="main olfactory bulb" />
</token>
<token canonical="primary motor cortex" ref_id="Hof:421">
  <variant base="primary motor cortex" />
</token>
<token canonical="secondary motor cortex" ref_id="Hof:426">
  <variant base="secondary motor cortex" />
</token>
<token canonical="posterior mammillary nucleus" ref_id="Hof:781735567">
  <variant base="posterior mammillary nucleus" />
</token>
<token canonical="medial preoptic nucleus, lateral part" ref_id="Hof:363">
  <variant base="medial preoptic nucleus, lateral part" />
</token>
<token canonical="medial preoptic nucleus, medial part" ref_id="Hof:363">
  <variant base="medial preoptic nucleus, medial part" />
</token>
<token canonical="medial preoptic area" ref_id="Hof:363">
  <variant base="medial preoptic area" />
</token>
<token canonical="medial pretectal nucleus" ref_id="Hof:-34766854">
  <variant base="medial pretectal nucleus" />
</token>
<token canonical="mesencephalic reticular nucleus" ref_id="Hof:-2110126000">
  <variant base="mesencephalic reticular nucleus" />
</token>
<token canonical="medial septum nucleus" ref_id="Hof:244">
  <variant base="medial septum nucleus" />
</token>
<token canonical="medial vestibular nucleus" ref_id="Hof:714">
  <variant base="medial vestibular nucleus" />
</token>
<token canonical="medial vestibular nucleus, magnocellular part" ref_id="Hof:714">
  <variant base="medial vestibular nucleus, magnocellular part" />
</token>
<token canonical="medial vestibular nucleus, parvicellular part" ref_id="Hof:714">
  <variant base="medial vestibular nucleus, parvicellular part" />
</token>
<token canonical="mid-cerebellar peduncle" ref_id="Hof:616">
  <variant base="mid-cerebellar peduncle" />
</token>
<token canonical="medial forebrain bundle" ref_id="Hof:416">
  <variant base="medial forebrain bundle" />
</token>
<token canonical="mitral cell layer" ref_id="Hof:261">
  <variant base="mitral cell layer" />
</token>
<token canonical="medial lemniscus" ref_id="Hof:736">
  <variant base="medial lemniscus" />
</token>
<token canonical="medial longitudinal fasciculus" ref_id="Hof:743">
  <variant base="medial longitudinal fasciculus" />
</token>
<token canonical="molecular layer of dentate gyrus" ref_id="Hof:584">
  <variant base="molecular layer of dentate gyrus" />
</token>
<token canonical="mammillary peduncle" ref_id="Hof:408">
  <variant base="mammillary peduncle" />
</token>
<token canonical="mammillotegmental tract" ref_id="Hof:406">
  <variant base="mammillotegmental tract" />
</token>
<token canonical="mammillothalamic tract" ref_id="Hof:115">
  <variant base="mammillothalamic tract" />
</token>
<token canonical="mesencephalic tract of the trigeminal nerve" ref_id="Hof:591">
  <variant base="mesencephalic tract of the trigeminal nerve" />
</token>
<token canonical="motor root of the trigeminal nerve" ref_id="Hof:604">
  <variant base="motor root of the trigeminal nerve" />
</token>
<token canonical="nucleus of the brachium of the inferior colliculus" ref_id="Hof:-203847533">
  <variant base="nucleus of the brachium of the inferior colliculus" />
</token>
<token canonical="nucleus of Darkschewitsch" ref_id="Hof:505">
  <variant base="nucleus of Darkschewitsch" />
</token>
<token canonical="nucleus of the diagonal band of Broca" ref_id="Hof:247">
  <variant base="nucleus of the diagonal band of Broca" />
</token>
<token canonical="nucleus intercalatus" ref_id="Hof:756">
  <variant base="nucleus intercalatus" />
</token>
<token canonical="nucleus of the lateral olfactory tract" ref_id="Hof:224">
  <variant base="nucleus of the lateral olfactory tract" />
</token>
<token canonical="nucleus of the posterior commissure" ref_id="Hof:502">
  <variant base="nucleus of the posterior commissure" />
</token>
<token canonical="nucleus of Roller" ref_id="Hof:760">
  <variant base="nucleus of Roller" />
</token>
<token canonical="nucleus of the trapezoid body" ref_id="Hof:571">
  <variant base="nucleus of the trapezoid body" />
</token>
<token canonical="nucleus of the solitary tract" ref_id="Hof:739">
  <variant base="nucleus of the solitary tract" />
</token>
<token canonical="optic nerve" ref_id="Hof:272">
  <variant base="optic nerve" />
</token>
<token canonical="trochlear nerve" ref_id="Hof:449">
  <variant base="trochlear nerve" />
</token>
<token canonical="nigrostriatal tract" ref_id="Hof:491">
  <variant base="nigrostriatal tract" />
</token>
<token canonical="trigeminal nerve" ref_id="Hof:540">
  <variant base="trigeminal nerve" />
</token>
<token canonical="facial nerve" ref_id="Hof:542">
  <variant base="facial nerve" />
</token>
<token canonical="vestibulocochlear nerve" ref_id="Hof:544">
  <variant base="vestibulocochlear nerve" />
</token>
<token canonical="hypoglossal nerve" ref_id="Hof:701">
  <variant base="hypoglossal nerve" />
</token>
<token canonical="occipital pole" ref_id="Hof:123">
  <variant base="occipital pole" />
</token>
<token canonical="olfactory nerve (nI)" ref_id="Hof:13">
  <variant base="olfactory nerve (nI)" />
</token>
<token canonical="olivary pretectal nucleus" ref_id="Hof:455">
  <variant base="olivary pretectal nucleus" />
</token>
<token canonical="orbital cortex, lateral part" ref_id="Hof:-57482258">
  <variant base="orbital cortex, lateral part" />
</token>
<token canonical="orbital cortex, medial part" ref_id="Hof:1004372860">
  <variant base="orbital cortex, medial part" />
</token>
<token canonical="orbital cortex, ventrolateral part" ref_id="Hof:122219355">
  <variant base="orbital cortex, ventrolateral part" />
</token>
<token canonical="olfactory tubercle" ref_id="Hof:264">
  <variant base="olfactory tubercle" />
</token>
<token canonical="vascular organ of the lamina terminalis" ref_id="Hof:366">
  <variant base="vascular organ of the lamina terminalis" />
</token>
<token canonical="olivocochlear bundle" ref_id="Hof:572">
  <variant base="olivocochlear bundle" />
</token>
<token canonical="optic chiasm" ref_id="Hof:442">
  <variant base="optic chiasm" />
</token>
<token canonical="optic layer of the superior colliculus" ref_id="Hof:73609237">
  <variant base="optic layer of the superior colliculus" />
</token>
<token canonical="outer plexiform layer" ref_id="Hof:261">
  <variant base="outer plexiform layer" />
</token>
<token canonical="optic tract" ref_id="Hof:443">
  <variant base="optic tract" />
</token>
<token canonical="posterior nucleus of the amygdala" ref_id="Hof:132">
  <variant base="posterior nucleus of the amygdala" />
</token>
<token canonical="periaqueductal gray matter" ref_id="Hof:501">
  <variant base="periaqueductal gray matter" />
</token>
<token canonical="paratrochlear nucleus" ref_id="Hof:-561393890">
  <variant base="paratrochlear nucleus" />
</token>
<token canonical="parvicellular reticular nucleus" ref_id="Hof:725">
  <variant base="parvicellular reticular nucleus" />
</token>
<token canonical="parasubiculum" ref_id="Hof:589">
  <variant base="parasubiculum" />
</token>
<token canonical="paratrigeminal nucleus" ref_id="Hof:758">
  <variant base="paratrigeminal nucleus" />
</token>
<token canonical="parabigeminal nucleus" ref_id="Hof:473">
  <variant base="parabigeminal nucleus" />
</token>
<token canonical="parabrachial nucleus, lateral central part" ref_id="Hof:583">
  <variant base="parabrachial nucleus, lateral central part" />
</token>
<token canonical="parabrachial nucleus, lateral dorsal part" ref_id="Hof:583">
  <variant base="parabrachial nucleus, lateral dorsal part" />
</token>
<token canonical="parabrachial nucleus, lateral external part" ref_id="Hof:583">
  <variant base="parabrachial nucleus, lateral external part" />
</token>
<token canonical="parabrachialnucleus, lateral superior part" ref_id="Hof:583">
  <variant base="parabrachialnucleus, lateral superior part" />
</token>
<token canonical="parabrachial nucleus, lateral ventral part" ref_id="Hof:583">
  <variant base="parabrachial nucleus, lateral ventral part" />
</token>
<token canonical="parabrachial nucleus, medial part" ref_id="Hof:582">
  <variant base="parabrachial nucleus, medial part" />
</token>
<token canonical="paracentral nucleus of the thalamus" ref_id="Hof:305">
  <variant base="paracentral nucleus of the thalamus" />
</token>
<token canonical="pontine central gray" ref_id="Hof:562">
  <variant base="pontine central gray" />
</token>
<token canonical="periventricular nucleus of the hypothalamus" ref_id="Hof:748">
  <variant base="periventricular nucleus of the hypothalamus" />
</token>
<token canonical="perirhinal cortex" ref_id="Hof:96">
  <variant base="perirhinal cortex" />
</token>
<token canonical="parafascicular nucleus of the thalamus" ref_id="Hof:307">
  <variant base="parafascicular nucleus of the thalamus" />
</token>
<token canonical="paraflocculus" ref_id="Hof:669">
  <variant base="paraflocculus" />
</token>
<token canonical="pontine gray matter" ref_id="Hof:613">
  <variant base="pontine gray matter" />
</token>
<token canonical="paragigantocellular reticular nucleus, dorsal part" ref_id="Hof:729">
  <variant base="paragigantocellular reticular nucleus, dorsal part" />
</token>
<token canonical="paragigantocellular reticular nucleus, lateral part" ref_id="Hof:728">
  <variant base="paragigantocellular reticular nucleus, lateral part" />
</token>
<token canonical="posterior hypothalamic area" ref_id="Hof:403">
  <variant base="posterior hypothalamic area" />
</token>
<token canonical="piriform cortex" ref_id="Hof:147">
  <variant base="piriform cortex" />
</token>
<token canonical="prelimbic area" ref_id="Hof:1039">
  <variant base="prelimbic area" />
</token>
<token canonical="paralemniscal nucleus" ref_id="Hof:1984320972">
  <variant base="paralemniscal nucleus" />
</token>
<token canonical="premammillary nucleus" ref_id="Hof:401">
  <variant base="premammillary nucleus" />
</token>
<token canonical="premammillary nucleus, dorsal part" ref_id="Hof:631">
  <variant base="premammillary nucleus, dorsal part" />
</token>
<token canonical="paramedian reticular nucleus" ref_id="Hof:734">
  <variant base="paramedian reticular nucleus" />
</token>
<token canonical="paranigral nucleus" ref_id="Hof:278">
  <variant base="paranigral nucleus" />
</token>
<token canonical="posterior complex of the thalamus" ref_id="Hof:343">
  <variant base="posterior complex of the thalamus" />
</token>
<token canonical="posterior limitans nucleus of the thalamus" ref_id="Hof:340">
  <variant base="posterior limitans nucleus of the thalamus" />
</token>
<token canonical="periolivary nuclei" ref_id="Hof:-869075658">
  <variant base="periolivary nuclei" />
</token>
<token canonical="peripeduncular nucleus" ref_id="Hof:511">
  <variant base="peripeduncular nucleus" />
</token>
<token canonical="pedunculopontine nucleus" ref_id="Hof:495">
  <variant base="pedunculopontine nucleus" />
</token>
<token canonical="posterior pretectal nucleus" ref_id="Hof:1412872736">
  <variant base="posterior pretectal nucleus" />
</token>
<token canonical="peripyramidal nucleus" ref_id="Hof:-1053574759">
  <variant base="peripyramidal nucleus" />
</token>
<token canonical="prerubral field" ref_id="Hof:423">
  <variant base="prerubral field" />
</token>
<token canonical="precommissural nucleus" ref_id="Hof:-1117507247">
  <variant base="precommissural nucleus" />
</token>
<token canonical="paramedian lobule of the cerebellum" ref_id="Hof:666">
  <variant base="paramedian lobule of the cerebellum" />
</token>
<token canonical="pontine reticular nucleus, caudal part" ref_id="Hof:561">
  <variant base="pontine reticular nucleus, caudal part" />
</token>
<token canonical="pontine reticular nucleus, rostral part" ref_id="Hof:560">
  <variant base="pontine reticular nucleus, rostral part" />
</token>
<token canonical="pontine reticular nucleus, ventral part" ref_id="Hof:-401234816">
  <variant base="pontine reticular nucleus, ventral part" />
</token>
<token canonical="nucleus prepositus" ref_id="Hof:755">
  <variant base="nucleus prepositus" />
</token>
<token canonical="presubiculum" ref_id="Hof:149">
  <variant base="presubiculum" />
</token>
<token canonical="parvalbumin-containing nucleus of the hypothalamus" ref_id="Hof:-1574102744">
  <variant base="parvalbumin-containing nucleus of the hypothalamus" />
</token>
<token canonical="parastriatal nucleus" ref_id="Hof:1709890647">
  <variant base="parastriatal nucleus" />
</token>
<token canonical="parasubthalamic nucleus" ref_id="Hof:-1270135926">
  <variant base="parasubthalamic nucleus" />
</token>
<token canonical="principal sensory nucleus of the trigeminal nerve" ref_id="Hof:552">
  <variant base="principal sensory nucleus of the trigeminal nerve" />
</token>
<token canonical="paratenial nucleus of the thalamus" ref_id="Hof:290">
  <variant base="paratenial nucleus of the thalamus" />
</token>
<token canonical="parietal association cortex, posterior area" ref_id="Hof:355206819">
  <variant base="parietal association cortex, posterior area" />
</token>
<token canonical="paraventricular nucleus of the hypothalamus" ref_id="Hof:370">
  <variant base="paraventricular nucleus of the hypothalamus" />
</token>
<token canonical="paraventricular nucleus of the thalamus" ref_id="Hof:291">
  <variant base="paraventricular nucleus of the thalamus" />
</token>
<token canonical="posterior commissure" ref_id="Hof:475">
  <variant base="posterior commissure" />
</token>
<token canonical="precentral fissure" ref_id="Hof:648">
  <variant base="precentral fissure" />
</token>
<token canonical="preculminate fissure" ref_id="Hof:649">
  <variant base="preculminate fissure" />
</token>
<token canonical="parafloccular sulcus" ref_id="Hof:-454300707">
  <variant base="parafloccular sulcus" />
</token>
<token canonical="posterolateral fissure" ref_id="Hof:646">
  <variant base="posterolateral fissure" />
</token>
<token canonical="principal mammillary tract" ref_id="Hof:405">
  <variant base="principal mammillary tract" />
</token>
<token canonical="polymorphic layer" ref_id="Hof:586">
  <variant base="polymorphic layer" />
</token>
<token canonical="prepyramidal fissure" ref_id="Hof:660">
  <variant base="prepyramidal fissure" />
</token>
<token canonical="primary fissure" ref_id="Hof:645">
  <variant base="primary fissure" />
</token>
<token canonical="posterior superior fissure" ref_id="Hof:659">
  <variant base="posterior superior fissure" />
</token>
<token canonical="perifacial zone" ref_id="Hof:-1271066332">
  <variant base="perifacial zone" />
</token>
<token canonical="pyramidal tract" ref_id="Hof:797">
  <variant base="pyramidal tract" />
</token>
<token canonical="decussation of the pyramidal tract" ref_id="Hof:796">
  <variant base="decussation of the pyramidal tract" />
</token>
<token canonical="retrochiasmatic hypothalamic area" ref_id="Hof:379">
  <variant base="retrochiasmatic hypothalamic area" />
</token>
<token canonical="reuniens nucleus of the thalamus" ref_id="Hof:292">
  <variant base="reuniens nucleus of the thalamus" />
</token>
<token canonical="retroethrnoidal nucleus of the thalamus" ref_id="Hof:1729658807">
  <variant base="retroethrnoidal nucleus of the thalamus" />
</token>
<token canonical="rhomboid nucleus of the thalamus" ref_id="Hof:293">
  <variant base="rhomboid nucleus of the thalamus" />
</token>
<token canonical="rostral interstitial nucleus of the medial longitudinal fasciculus" ref_id="Hof:507">
  <variant base="rostral interstitial nucleus of the medial longitudinal fasciculus" />
</token>
<token canonical="rostral linear nucleus of the raphe" ref_id="Hof:510">
  <variant base="rostral linear nucleus of the raphe" />
</token>
<token canonical="nucleus raphe magnus" ref_id="Hof:736">
  <variant base="nucleus raphe magnus" />
</token>
<token canonical="red nucleus" ref_id="Hof:496">
  <variant base="red nucleus" />
</token>
<token canonical="red nucleus, magnocellular part" ref_id="Hof:498">
  <variant base="red nucleus, magnocellular part" />
</token>
<token canonical="red nucleus, parvicellular part" ref_id="Hof:497">
  <variant base="red nucleus, parvicellular part" />
</token>
<token canonical="nucleus raphe obscurus" ref_id="Hof:737">
  <variant base="nucleus raphe obscurus" />
</token>
<token canonical="nucleus raphe pallidus" ref_id="Hof:738">
  <variant base="nucleus raphe pallidus" />
</token>
<token canonical="retroparafascicular nucleus" ref_id="Hof:1081283401">
  <variant base="retroparafascicular nucleus" />
</token>
<token canonical="retrorubral field" ref_id="Hof:1854054867">
  <variant base="retrorubral field" />
</token>
<token canonical="retrorubral field, dopaminergic A8 group" ref_id="Hof:1854054867">
  <variant base="retrorubral field, dopaminergic A8 group" />
</token>
<token canonical="retrosplenial cortex, dorsal part" ref_id="Hof:1834734299">
  <variant base="retrosplenial cortex, dorsal part" />
</token>
<token canonical="retrosplenial cortex, ventral part" ref_id="Hof:-197316282">
  <variant base="retrosplenial cortex, ventral part" />
</token>
<token canonical="reticular nucleus of the thalamus" ref_id="Hof:348">
  <variant base="reticular nucleus of the thalamus" />
</token>
<token canonical="rostroventrolateral reticular nucleus" ref_id="Hof:-993361331">
  <variant base="rostroventrolateral reticular nucleus" />
</token>
<token canonical="rhinal fissure" ref_id="Hof:22">
  <variant base="rhinal fissure" />
</token>
<token canonical="rubrospinal tract" ref_id="Hof:803">
  <variant base="rubrospinal tract" />
</token>
<token canonical="nucleus sagulum" ref_id="Hof:359">
  <variant base="nucleus sagulum" />
</token>
<token canonical="superior colliculus" ref_id="Hof:456">
  <variant base="superior colliculus" />
</token>
<token canonical="suprachiasmatic nucleus" ref_id="Hof:367">
  <variant base="suprachiasmatic nucleus" />
</token>
<token canonical="subcommissural organ" ref_id="Hof:474">
  <variant base="subcommissural organ" />
</token>
<token canonical="subependymal zone" ref_id="Hof:-1951800997">
  <variant base="subependymal zone" />
</token>
<token canonical="septofimbrial nucleus" ref_id="Hof:246">
  <variant base="septofimbrial nucleus" />
</token>
<token canonical="subfornical organ" ref_id="Hof:437">
  <variant base="subfornical organ" />
</token>
<token canonical="substantia gelatinosa" ref_id="Hof:921">
  <variant base="substantia gelatinosa" />
</token>
<token canonical="subgeniculate nucleus" ref_id="Hof:-147481314">
  <variant base="subgeniculate nucleus" />
</token>
<token canonical="septohippocampal nucleus" ref_id="Hof:618">
  <variant base="septohippocampal nucleus" />
</token>
<token canonical="substantia innominata" ref_id="Hof:256">
  <variant base="substantia innominata" />
</token>
<token canonical="simple lobule of the cerebellum" ref_id="Hof:662">
  <variant base="simple lobule of the cerebellum" />
</token>
<token canonical="submedial nucleus of the thalamus" ref_id="Hof:347">
  <variant base="submedial nucleus of the thalamus" />
</token>
<token canonical="substantia nigra, compact part" ref_id="Hof:528">
  <variant base="substantia nigra, compact part" />
</token>
<token canonical="substantia nigra, lateral part" ref_id="Hof:180">
  <variant base="substantia nigra, lateral part" />
</token>
<token canonical="substantia nigra, reticular part" ref_id="Hof:529">
  <variant base="substantia nigra, reticular part" />
</token>
<token canonical="supraoptic nucleus" ref_id="Hof:368">
  <variant base="supraoptic nucleus" />
</token>
<token canonical="superior olivary complex, lateral part" ref_id="Hof:566">
  <variant base="superior olivary complex, lateral part" />
</token>
<token canonical="superior olivary complex, medial part" ref_id="Hof:567">
  <variant base="superior olivary complex, medial part" />
</token>
<token canonical="subparafascicular nucleus of the thalamus" ref_id="Hof:38">
  <variant base="subparafascicular nucleus of the thalamus" />
</token>
<token canonical="suprageniculate nucleus" ref_id="Hof:346">
  <variant base="suprageniculate nucleus" />
</token>
<token canonical="sphenoid nucleus" ref_id="Hof:18316578">
  <variant base="sphenoid nucleus" />
</token>
<token canonical="spinal nucleus of the trigeminal nerve, caudal part" ref_id="Hof:1015266456">
  <variant base="spinal nucleus of the trigeminal nerve, caudal part" />
</token>
<token canonical="spinal nucleus of the trigeminal nerve, interpolar part" ref_id="Hof:1015266456">
  <variant base="spinal nucleus of the trigeminal nerve, interpolar part" />
</token>
<token canonical="spinal vestibular nucleus" ref_id="Hof:715">
  <variant base="spinal vestibular nucleus" />
</token>
<token canonical="spinal nucleus of the trigeminal nerve, oral dorsomedial part" ref_id="Hof:1015266456">
  <variant base="spinal nucleus of the trigeminal nerve, oral dorsomedial part" />
</token>
<token canonical="spinal nucleus of the trigeminal nerve, oral ventrolateral part" ref_id="Hof:1015266456">
  <variant base="spinal nucleus of the trigeminal nerve, oral ventrolateral part" />
</token>
<token canonical="primary somatosensory cortex" ref_id="Hof:419">
  <variant base="primary somatosensory cortex" />
</token>
<token canonical="secondary somatosensory cortex" ref_id="Hof:420">
  <variant base="secondary somatosensory cortex" />
</token>
<token canonical="subthalamic nucleus" ref_id="Hof:418">
  <variant base="subthalamic nucleus" />
</token>
<token canonical="subiculum" ref_id="Hof:170">
  <variant base="subiculum" />
</token>
<token canonical="subincertal nucleus" ref_id="Hof:-454258616">
  <variant base="subincertal nucleus" />
</token>
<token canonical="supraoculomotor nucleus" ref_id="Hof:-1304747118">
  <variant base="supraoculomotor nucleus" />
</token>
<token canonical="supramammillary nucleus" ref_id="Hof:400">
  <variant base="supramammillary nucleus" />
</token>
<token canonical="supramammillary nucleus, lateral part" ref_id="Hof:-966771805">
  <variant base="supramammillary nucleus, lateral part" />
</token>
<token canonical="supramammillary nucleus, medial part" ref_id="Hof:-393964923">
  <variant base="supramammillary nucleus, medial part" />
</token>
<token canonical="superior vestibular nucleus" ref_id="Hof:712">
  <variant base="superior vestibular nucleus" />
</token>
<token canonical="superior cerebellar peduncle" ref_id="Hof:1289712953">
  <variant base="superior cerebellar peduncle" />
</token>
<token canonical="secondary fissure" ref_id="Hof:641">
  <variant base="secondary fissure" />
</token>
<token canonical="granule cell layer" ref_id="Hof:585">
  <variant base="granule cell layer" />
</token>
<token canonical="superficial gray layer of the superior colliculus" ref_id="Hof:453472987">
  <variant base="superficial gray layer of the superior colliculus" />
</token>
<token canonical="simple fissure" ref_id="Hof:512116441">
  <variant base="simple fissure" />
</token>
<token canonical="stratum lacunosum moleculare" ref_id="Hof:137">
  <variant base="stratum lacunosum moleculare" />
</token>
<token canonical="stratum lucidum" ref_id="Hof:-975815906">
  <variant base="stratum lucidum" />
</token>
<token canonical="stria medullaris" ref_id="Hof:281">
  <variant base="stria medullaris" />
</token>
<token canonical="stratum oriens" ref_id="Hof:139">
  <variant base="stratum oriens" />
</token>
<token canonical="stratum pyramidale" ref_id="Hof:138">
  <variant base="stratum pyramidale" />
</token>
<token canonical="spinal tract of the trigeminal nerve" ref_id="Hof:744">
  <variant base="spinal tract of the trigeminal nerve" />
</token>
<token canonical="stratum radiatum" ref_id="Hof:140">
  <variant base="stratum radiatum" />
</token>
<token canonical="stria terminalis" ref_id="Hof:268">
  <variant base="stria terminalis" />
</token>
<token canonical="superior thalamic radiation" ref_id="Hof:396">
  <variant base="superior thalamic radiation" />
</token>
<token canonical="supraoptic commissure" ref_id="Hof:482">
  <variant base="supraoptic commissure" />
</token>
<token canonical="sensory root of the trigeminal nerve" ref_id="Hof:485">
  <variant base="sensory root of the trigeminal nerve" />
</token>
<token canonical="terete nucleus of the hypothalamus" ref_id="Hof:-711877820">
  <variant base="terete nucleus of the hypothalamus" />
</token>
<token canonical="temporal association cortex" ref_id="Hof:374777352">
  <variant base="temporal association cortex" />
</token>
<token canonical="tuberomammillary nucleus, dorsal part" ref_id="Hof:1726369909">
  <variant base="tuberomammillary nucleus, dorsal part" />
</token>
<token canonical="tuberomammillary nucleus, ventral part" ref_id="Hof:-1416727325">
  <variant base="tuberomammillary nucleus, ventral part" />
</token>
<token canonical="tegmental reticular nucleus" ref_id="Hof:563">
  <variant base="tegmental reticular nucleus" />
</token>
<token canonical="triangular nucleus of the septum" ref_id="Hof:245">
  <variant base="triangular nucleus of the septum" />
</token>
<token canonical="tenia tecta, dorsal part" ref_id="Hof:21114008">
  <variant base="tenia tecta, dorsal part" />
</token>
<token canonical="tenia tecta, ventral part" ref_id="Hof:-1374190671">
  <variant base="tenia tecta, ventral part" />
</token>
<token canonical="tuberal nucleus" ref_id="Hof:1933488759">
  <variant base="tuberal nucleus" />
</token>
<token canonical="trapezoid body" ref_id="Hof:589">
  <variant base="trapezoid body" />
</token>
<token canonical="transverse fibers of the pons" ref_id="Hof:615">
  <variant base="transverse fibers of the pons" />
</token>
<token canonical="tractus solitarius" ref_id="Hof:782">
  <variant base="tractus solitarius" />
</token>
<token canonical="tectospinal tract" ref_id="Hof:783">
  <variant base="tectospinal tract" />
</token>
<token canonical="motor nucleus of the trigeminal nerve" ref_id="Hof:551">
  <variant base="motor nucleus of the trigeminal nerve" />
</token>
<token canonical="third ventricle" ref_id="Hof:429">
  <variant base="third ventricle" />
</token>
<token canonical="fourth ventricle" ref_id="Hof:617">
  <variant base="fourth ventricle" />
</token>
<token canonical="ventral anterior nucleus of the thalamus" ref_id="Hof:317">
  <variant base="ventral anterior nucleus of the thalamus" />
</token>
<token canonical="ventral anterolateral nucleus of the thalamus" ref_id="Hof:208927283">
  <variant base="ventral anterolateral nucleus of the thalamus" />
</token>
<token canonical="vestibulocerebellar nucleus" ref_id="Hof:-439062383">
  <variant base="vestibulocerebellar nucleus" />
</token>
<token canonical="ventral cochlear nucleus, anterior part" ref_id="Hof:-1080372086">
  <variant base="ventral cochlear nucleus, anterior part" />
</token>
<token canonical="ventral cochlear nucleus, posterior part" ref_id="Hof:952072315">
  <variant base="ventral cochlear nucleus, posterior part" />
</token>
<token canonical="ventral horn of the spinal cord" ref_id="Hof:923">
  <variant base="ventral horn of the spinal cord" />
</token>
<token canonical="abducens nucleus" ref_id="Hof:580">
  <variant base="abducens nucleus" />
</token>
<token canonical="facial nucleus" ref_id="Hof:581">
  <variant base="facial nucleus" />
</token>
<token canonical="visual cortex, anterolateral part" ref_id="Hof:1099194475">
  <variant base="visual cortex, anterolateral part" />
</token>
<token canonical="visual cortex, anteromedial part" ref_id="Hof:1099194475">
  <variant base="visual cortex, anteromedial part" />
</token>
<token canonical="visceral area" ref_id="Hof:-1901460249">
  <variant base="visceral area" />
</token>
<token canonical="visual cortex, lateral part" ref_id="Hof:1099194475">
  <variant base="visual cortex, lateral part" />
</token>
<token canonical="primary visual cortex" ref_id="Hof:415">
  <variant base="primary visual cortex" />
</token>
<token canonical="visual cortex, posterolateral part" ref_id="Hof:1099194475">
  <variant base="visual cortex, posterolateral part" />
</token>
<token canonical="visual cortex, posteromedial part" ref_id="Hof:1099194475">
  <variant base="visual cortex, posteromedial part" />
</token>
<token canonical="visual cortex, rostrolateral area" ref_id="Hof:1099194475">
  <variant base="visual cortex, rostrolateral area" />
</token>
<token canonical="lateral ventricle" ref_id="Hof:191">
  <variant base="lateral ventricle" />
</token>
<token canonical="ventral nucleus of the lateral lemniscus" ref_id="Hof:587">
  <variant base="ventral nucleus of the lateral lemniscus" />
</token>
<token canonical="ventrolateral tegmental area" ref_id="Hof:-768859151">
  <variant base="ventrolateral tegmental area" />
</token>
<token canonical="ventromedial nucleus of the thalamus" ref_id="Hof:-1446111096">
  <variant base="ventromedial nucleus of the thalamus" />
</token>
<token canonical="ventromedial nucleus of the hypothalamus" ref_id="Hof:381">
  <variant base="ventromedial nucleus of the hypothalamus" />
</token>
<token canonical="ventromedial nucleus of the hypothalamus, central part" ref_id="Hof:381">
  <variant base="ventromedial nucleus of the hypothalamus, central part" />
</token>
<token canonical="ventromedial nucleus of the hypothalamus, dorsomedial part" ref_id="Hof:381">
  <variant base="ventromedial nucleus of the hypothalamus, dorsomedial part" />
</token>
<token canonical="ventromedial nucleus of the hypothalamus, ventrolateral part" ref_id="Hof:381">
  <variant base="ventromedial nucleus of the hypothalamus, ventrolateral part" />
</token>
<token canonical="ventroposterolateral nucleus of the thalamus" ref_id="Hof:327">
  <variant base="ventroposterolateral nucleus of the thalamus" />
</token>
<token canonical="ventroposteromedial nucleus of the thalamus" ref_id="Hof:330">
  <variant base="ventroposteromedial nucleus of the thalamus" />
</token>
<token canonical="ventral reticular nucleus" ref_id="Hof:730">
  <variant base="ventral reticular nucleus" />
</token>
<token canonical="ventral tegmental area" ref_id="Hof:512">
  <variant base="ventral tegmental area" />
</token>
<token canonical="ventral tegmental nucleus" ref_id="Hof:509">
  <variant base="ventral tegmental nucleus" />
</token>
<token canonical="ventral hippocampal commissure" ref_id="Hof:-278898222">
  <variant base="ventral hippocampal commissure" />
</token>
<token canonical="vomeronasal nerve" ref_id="Hof:711">
  <variant base="vomeronasal nerve" />
</token>
<token canonical="ventral spinocerebellar tract" ref_id="Hof:805">
  <variant base="ventral spinocerebellar tract" />
</token>
<token canonical="ventral tegmental decussation" ref_id="Hof:515">
  <variant base="ventral tegmental decussation" />
</token>
<token canonical="vestibulocochlear nerve, vestibular root" ref_id="Hof:468">
  <variant base="vestibulocochlear nerve, vestibular root" />
</token>
<token canonical="nucleus X" ref_id="Hof:1460531574">
  <variant base="nucleus X" />
</token>
<token canonical="xiphoid nucleus of the thalamus" ref_id="Hof:-1399738243">
  <variant base="xiphoid nucleus of the thalamus" />
</token>
<token canonical="hypoglossal nucleus" ref_id="Hof:754">
  <variant base="hypoglossal nucleus" />
</token>
<token canonical="zona incerta" ref_id="Hof:421">
  <variant base="zona incerta" />
</token>
<token canonical="zona limitans" ref_id="Hof:1386443582">
  <variant base="zona limitans" />
</token>
<token canonical="zonal layer of the superior colliculus" ref_id="Hof:555439230">
  <variant base="zonal layer of the superior colliculus" />
</token>
</synonym>
